pyxeoma/__init__.py
pyxeoma/xeoma.py
pyxeoma-1.4.2.dist-info/LICENSE
pyxeoma-1.4.2.dist-info/METADATA
pyxeoma-1.4.2.dist-info/WHEEL
pyxeoma-1.4.2.dist-info/top_level.txt
pyxeoma-1.4.2.dist-info/RECORD
