Metadata-Version: 1.1
Name: pyxeoma
Version: 1.4.2
Summary: Python wrapper for Xeoma web server API
Home-page: https://github.com/jeradM/pyxeoma
Author: Jerad Meisner
Author-email: jerad.meisner@gmail.com
License: MIT
Download-URL: https://github.com/jeradM/pyxeoma/archive/1.4.2.tar.gz
Keywords: Xeoma
Platform: UNKNOWN
